Metadata-Version: 2.1
Name: nonebot-plugin-sleep
Version: 0.1.1
Summary: 来一份精致的睡眠套餐
Home-page: https://github.com/mas-alone/nonebot-plugin-sleep
Author: A M D
Author-email: mas_alone@qq.com
Classifier: Programming Language :: Python :: 3.8
Classifier: License :: OSI Approved :: GNU Affero General Public License v3
Classifier: Operating System :: OS Independent
License-File: LICENSE
Requires-Dist: nonebot2 >=2.0.0rc3
Requires-Dist: nonebot-adapter-onebot >=2.0.0b1
